snail_orbit_client/__init__.py
snail_orbit_client/auth.py
snail_orbit_client/client.py
snail_orbit_client/config.py
snail_orbit_client/constants.py
snail_orbit_client/exceptions.py
snail_orbit_client/core/__init__.py
snail_orbit_client/core/protocols.py
snail_orbit_client/core/session.py
snail_orbit_client/core/transport.py
snail_orbit_client/models/__init__.py
snail_orbit_client/models/_base.py
snail_orbit_client/models/_types.py
snail_orbit_client/models/activity.py
snail_orbit_client/models/auth.py
snail_orbit_client/models/base.py
snail_orbit_client/models/custom_fields.py
snail_orbit_client/models/issues.py
snail_orbit_client/models/projects.py
snail_orbit_client/models/system.py
snail_orbit_client/models/users.py
snail_orbit_client/resources/__init__.py
snail_orbit_client/resources/activity.py
snail_orbit_client/resources/auth.py
snail_orbit_client/resources/base.py
snail_orbit_client/resources/custom_fields.py
snail_orbit_client/resources/issues.py
snail_orbit_client/resources/projects.py
snail_orbit_client/resources/users.py
snail_orbit_client-0.11.1.dist-info/METADATA
snail_orbit_client-0.11.1.dist-info/WHEEL
snail_orbit_client-0.11.1.dist-info/RECORD
