Metadata-Version: 2.4
Name: snail-orbit-client
Version: 0.11.1
Summary: Type-safe Python client for Snail Orbit project management system with read operations and issue management
Author-email: Snail Orbit Team <dev@snorbit.app>
Keywords: api-client,project-management,snail-orbit,task-tracking
Classifier: Development Status :: 4 - Beta
Classifier: Intended Audience :: Developers
Classifier: License :: OSI Approved :: MIT License
Classifier: Programming Language :: Python :: 3.11
Classifier: Programming Language :: Python :: 3.12
Classifier: Programming Language :: Python :: 3.13
Classifier: Topic :: Software Development :: Libraries :: Python Modules
Requires-Python: >=3.11
Requires-Dist: httpx>=0.25.0
Requires-Dist: pydantic>=2.0.0
Requires-Dist: pyjwt[crypto]>=2.8.0
